LICENSE
MANIFEST.in
README.rst
setup.py
PyFlot.egg-info/PKG-INFO
PyFlot.egg-info/SOURCES.txt
PyFlot.egg-info/dependency_links.txt
PyFlot.egg-info/top_level.txt
flot/__init__.py
flot/exception.py
flot/models.py
flot/templates/graph.html
flot/templatetags/__init__.py
flot/templatetags/flot_tags.py