Metadata-Version: 1.1
Name: PyFlot
Version: 0.2
Summary: Python Interface the JavaScript Flot chart librabry
Home-page: http://github.com/andrefsp/pyflot
Author: Andre da Palma
Author-email: andrefsp@gmail.com
License: MIT
Platform: UNKNOWN
Classifier: License :: OSI Approved :: MIT License
Classifier: Programming Language :: Python
Classifier: Programming Language :: JavaScript
Classifier: Operating System :: OS Independent
Classifier: Topic :: Internet
Classifier: Topic :: Utilities
Classifier: Topic :: Software Development :: Libraries
